pyquestaal
