Metadata-Version: 2.1
Name: pyquestaal
Version: 0.2.3
Summary: Python class to interface with QUESTAAL Quantum codes which is a suite of electronic structure programs.
Home-page: https://github.com/santoshkumarradha/pyquestaal
Author: Santosh Kumar Radha
Author-email: srr70@case.edu
License: UNKNOWN
Platform: UNKNOWN
Classifier: Development Status :: 3 - Alpha
Classifier: Intended Audience :: Developers
Classifier: Topic :: Software Development :: Build Tools
Classifier: License :: OSI Approved :: MIT License
Classifier: Programming Language :: Python :: 3
Classifier: Programming Language :: Python :: 3.7
Classifier: Programming Language :: Python :: 3.8
Classifier: Programming Language :: Python :: 3.9
Classifier: Programming Language :: Python :: 3.10
Classifier: Programming Language :: Python :: 3 :: Only
Requires-Python: >=3.6, <4
License-File: LICENSE.rst
